math_tool/__init__.py
math_tool/operation.py
math_tool/statistics.py
math_tool/calculus/__init__.py
math_tool/calculus/integrations.py
math_tool/geometry/__init__.py
math_tool/geometry/shapes.py
math_tool-1.0.0.dist-info/METADATA
math_tool-1.0.0.dist-info/WHEEL
math_tool-1.0.0.dist-info/top_level.txt
math_tool-1.0.0.dist-info/RECORD
