Metadata-Version: 2.1
Name: math-tool
Version: 1.0.0
Summary: A collection of mathematical utility functions
Author: Tom Alex
Requires-Dist: numpy
Requires-Dist: scipy
